[
    {
        "SupplierID": "S001",
        "SupplierName": "Powers-Sanders",
        "ContactPerson": "Dana Porter",
        "PhoneNumber": "(847)685-1970",
        "Email": "thomasjennifer@gmail.com",
        "Address": "8742 Porter Cliff\nEast Marc, KS 70978",
        "ProductCategoriesSupplied": "Kids"
    },
    {
        "SupplierID": "S002",
        "SupplierName": "Rodriguez-Forbes",
        "ContactPerson": "William Lynn",
        "PhoneNumber": "966.971.8451",
        "Email": "codycross@gmail.com",
        "Address": "PSC 3930, Box 8052\nAPO AA 57872",
        "ProductCategoriesSupplied": "Kids, Accessories, Men"
    },
    {
        "SupplierID": "S003",
        "SupplierName": "Jones-Williams",
        "ContactPerson": "Jennifer Lopez",
        "PhoneNumber": "1029294157",
        "Email": "hbrown@yahoo.com",
        "Address": "2623 Taylor Groves\nWest Charles, CA 87818",
        "ProductCategoriesSupplied": "Accessories, Women, Kids"
    },
    {
        "SupplierID": "S004",
        "SupplierName": "Griffin and Sons",
        "ContactPerson": "Peter Hernandez",
        "PhoneNumber": "633.197.8357x841",
        "Email": "fischercynthia@davis.biz",
        "Address": "6819 Fields Green Apt. 798\nAndreabury, IN 96137",
        "ProductCategoriesSupplied": "Kids, Accessories"
    },
    {
        "SupplierID": "S005",
        "SupplierName": "Schmidt Inc",
        "ContactPerson": "John Barnes",
        "PhoneNumber": "529.274.6012",
        "Email": "john40@yahoo.com",
        "Address": "PSC 1156, Box 2524\nAPO AP 31739",
        "ProductCategoriesSupplied": "Accessories"
    },
    {
        "SupplierID": "S006",
        "SupplierName": "Johnson-Cooper",
        "ContactPerson": "Tony Ford",
        "PhoneNumber": "(633)974-7633x1007",
        "Email": "barnesalexander@gmail.com",
        "Address": "24257 Catherine Villages Suite 160\nDanielville, AL 97354",
        "ProductCategoriesSupplied": "Accessories, Women"
    },
    {
        "SupplierID": "S007",
        "SupplierName": "Mann, Cook and Brown",
        "ContactPerson": "Sharon Oliver",
        "PhoneNumber": "388.126.8912x947",
        "Email": "shermanjay@hotmail.com",
        "Address": "269 Hayes Circles Apt. 722\nKarenburgh, WV 44786",
        "ProductCategoriesSupplied": "Women"
    },
    {
        "SupplierID": "S008",
        "SupplierName": "Curtis PLC",
        "ContactPerson": "Kyle Martin",
        "PhoneNumber": "790.171.0085x21531",
        "Email": "turnerstephanie@yahoo.com",
        "Address": "7518 Peter Street Apt. 396\nNew Melissaberg, CT 80989",
        "ProductCategoriesSupplied": "Women"
    },
    {
        "SupplierID": "S009",
        "SupplierName": "Phillips LLC",
        "ContactPerson": "Tyler Martinez",
        "PhoneNumber": "001-443-162-6380x9326",
        "Email": "kyle20@hayes.com",
        "Address": "8699 Ruth Oval Suite 745\nChristopherfurt, WV 69921",
        "ProductCategoriesSupplied": "Accessories, Men"
    },
    {
        "SupplierID": "S010",
        "SupplierName": "Bolton-Carpenter",
        "ContactPerson": "Tammy Jenkins",
        "PhoneNumber": "+1-091-886-8063x1680",
        "Email": "anthonyalexander@gmail.com",
        "Address": "762 Phillip Views\nPort Jeremy, UT 44988",
        "ProductCategoriesSupplied": "Men, Kids, Women"
    },
    {
        "SupplierID": "S011",
        "SupplierName": "Mckay-Lewis",
        "ContactPerson": "Billy Brown",
        "PhoneNumber": "039-915-0858",
        "Email": "davidbrown@clay.info",
        "Address": "9576 Owens Green\nBallardburgh, ND 00700",
        "ProductCategoriesSupplied": "Kids, Women, Accessories"
    },
    {
        "SupplierID": "S012",
        "SupplierName": "Hall LLC",
        "ContactPerson": "Brian Hernandez",
        "PhoneNumber": "+1-182-530-4248x86626",
        "Email": "thompsonbrianna@gmail.com",
        "Address": "886 Angela Camp Suite 292\nWest Jeffreyfurt, CO 05529",
        "ProductCategoriesSupplied": "Men, Kids, Women"
    },
    {
        "SupplierID": "S013",
        "SupplierName": "Nguyen, Morris and Vaughn",
        "ContactPerson": "Ana Drake",
        "PhoneNumber": "1234586203",
        "Email": "brownbruce@yahoo.com",
        "Address": "PSC 1978, Box 2882\nAPO AE 81213",
        "ProductCategoriesSupplied": "Men, Women"
    },
    {
        "SupplierID": "S014",
        "SupplierName": "Kim-Woods",
        "ContactPerson": "Nicole Payne",
        "PhoneNumber": "(074)314-6202x76407",
        "Email": "amy31@hotmail.com",
        "Address": "1736 Vargas Way\nWest Robert, PA 81955",
        "ProductCategoriesSupplied": "Kids"
    },
    {
        "SupplierID": "S015",
        "SupplierName": "Carr, Williams and Jones",
        "ContactPerson": "Gregory Gray",
        "PhoneNumber": "968-773-9738",
        "Email": "trevor06@robertson.com",
        "Address": "1100 Acevedo Knoll\nNew Ritashire, CA 29950",
        "ProductCategoriesSupplied": "Accessories, Men, Kids"
    },
    {
        "SupplierID": "S016",
        "SupplierName": "Rogers-Schmitt",
        "ContactPerson": "Amber Owens",
        "PhoneNumber": "907-274-5021x497",
        "Email": "ryan34@gmail.com",
        "Address": "4624 Benton Tunnel\nNew Ryanland, VT 04028",
        "ProductCategoriesSupplied": "Men"
    },
    {
        "SupplierID": "S017",
        "SupplierName": "Miller PLC",
        "ContactPerson": "Eric Walker",
        "PhoneNumber": "489.895.1847x46863",
        "Email": "caroline26@yahoo.com",
        "Address": "179 Michael Fields\nGomezmouth, TX 53963",
        "ProductCategoriesSupplied": "Kids, Men"
    },
    {
        "SupplierID": "S018",
        "SupplierName": "Simpson-Powers",
        "ContactPerson": "Harold Browning MD",
        "PhoneNumber": "470-701-5007",
        "Email": "anthony53@gmail.com",
        "Address": "613 Amanda Inlet Suite 846\nKimfurt, KS 67373",
        "ProductCategoriesSupplied": "Accessories, Women, Men"
    },
    {
        "SupplierID": "S019",
        "SupplierName": "Joseph-Garcia",
        "ContactPerson": "Zoe Bolton",
        "PhoneNumber": "099-149-5822x851",
        "Email": "timothy22@hotmail.com",
        "Address": "4334 Laurie Inlet Apt. 732\nEast Clarenceport, AK 06509",
        "ProductCategoriesSupplied": "Kids, Men"
    },
    {
        "SupplierID": "S020",
        "SupplierName": "Martinez-Smith",
        "ContactPerson": "Amy Moore",
        "PhoneNumber": "(543)531-2459x602",
        "Email": "rebeccaflores@herrera.info",
        "Address": "77353 Brown Spur Apt. 838\nEast Jessica, ME 64675",
        "ProductCategoriesSupplied": "Women, Kids"
    },
    {
        "SupplierID": "S021",
        "SupplierName": "Foster, Richmond and Maldonado",
        "ContactPerson": "Joyce Rodriguez",
        "PhoneNumber": "001-781-102-2208",
        "Email": "andrew62@hotmail.com",
        "Address": "6402 Rogers Stream Suite 902\nNew Jasonport, NV 90656",
        "ProductCategoriesSupplied": "Men"
    },
    {
        "SupplierID": "S022",
        "SupplierName": "Brown, Crawford and Anderson",
        "ContactPerson": "Heather Johnson",
        "PhoneNumber": "001-498-755-4149x829",
        "Email": "usmith@keith-sosa.com",
        "Address": "61253 James River\nLake Nicole, DC 27284",
        "ProductCategoriesSupplied": "Women"
    },
    {
        "SupplierID": "S023",
        "SupplierName": "Hernandez, Buckley and Perez",
        "ContactPerson": "Dylan Anderson",
        "PhoneNumber": "288.239.5533",
        "Email": "clin@hanna.com",
        "Address": "PSC 4025, Box 6221\nAPO AP 88983",
        "ProductCategoriesSupplied": "Accessories, Women, Kids"
    },
    {
        "SupplierID": "S024",
        "SupplierName": "Miller PLC",
        "ContactPerson": "Andrea Porter",
        "PhoneNumber": "203-331-5892x9454",
        "Email": "noah44@freeman.biz",
        "Address": "81351 Richardson Mount Suite 406\nJohnsonbury, MT 74506",
        "ProductCategoriesSupplied": "Kids, Men, Accessories"
    },
    {
        "SupplierID": "S025",
        "SupplierName": "Lester-Flores",
        "ContactPerson": "Lisa Davis",
        "PhoneNumber": "595.871.2561",
        "Email": "millerjoel@hotmail.com",
        "Address": "219 Brian Hill\nNew Kristenfort, ME 37510",
        "ProductCategoriesSupplied": "Accessories, Kids, Women"
    },
    {
        "SupplierID": "S026",
        "SupplierName": "Jones-Thompson",
        "ContactPerson": "Randy Miller",
        "PhoneNumber": "004.815.3662",
        "Email": "james87@gmail.com",
        "Address": "92180 Connor Oval\nPort Timothy, WV 03197",
        "ProductCategoriesSupplied": "Men, Women"
    },
    {
        "SupplierID": "S027",
        "SupplierName": "Johnson-Carson",
        "ContactPerson": "Annette Washington",
        "PhoneNumber": "449.324.3189",
        "Email": "rweiss@adams.com",
        "Address": "10648 Christina Lodge Suite 981\nGomezville, FL 45755",
        "ProductCategoriesSupplied": "Women, Kids"
    },
    {
        "SupplierID": "S028",
        "SupplierName": "Gardner and Sons",
        "ContactPerson": "Connie Miller",
        "PhoneNumber": "001-790-497-2472x19857",
        "Email": "johnny79@gmail.com",
        "Address": "7604 Costa Motorway\nWest Sheilafort, MA 26237",
        "ProductCategoriesSupplied": "Women, Kids, Men"
    },
    {
        "SupplierID": "S029",
        "SupplierName": "Calhoun, Osborne and Williams",
        "ContactPerson": "Jessica Merritt",
        "PhoneNumber": "139-775-0713",
        "Email": "shawnburns@gmail.com",
        "Address": "63813 West Pike\nSouth Caseyhaven, UT 81526",
        "ProductCategoriesSupplied": "Kids"
    },
    {
        "SupplierID": "S030",
        "SupplierName": "White Group",
        "ContactPerson": "Jessica Craig",
        "PhoneNumber": "(374)200-0305",
        "Email": "stacey56@rodriguez.com",
        "Address": "285 Smith Club Apt. 488\nCaitlinville, CO 83598",
        "ProductCategoriesSupplied": "Accessories, Women"
    },
    {
        "SupplierID": "S031",
        "SupplierName": "Dillon LLC",
        "ContactPerson": "Chelsey Holloway",
        "PhoneNumber": "075.909.2475x81044",
        "Email": "gillespiedana@howard-murphy.com",
        "Address": "65575 Christie Port\nSampsonshire, IN 57329",
        "ProductCategoriesSupplied": "Men, Accessories, Kids"
    },
    {
        "SupplierID": "S032",
        "SupplierName": "Lowe LLC",
        "ContactPerson": "Tiffany Lopez",
        "PhoneNumber": "0770294641",
        "Email": "cwilson@gmail.com",
        "Address": "61642 Barbara Plaza\nSouth Katherinefurt, OR 06758",
        "ProductCategoriesSupplied": "Men, Women"
    },
    {
        "SupplierID": "S033",
        "SupplierName": "Maxwell, Martin and Sanchez",
        "ContactPerson": "Michael Johnston",
        "PhoneNumber": "517-916-4750x1087",
        "Email": "henry78@jackson.net",
        "Address": "4649 Rowe Loaf\nEricland, MN 66285",
        "ProductCategoriesSupplied": "Accessories, Men"
    },
    {
        "SupplierID": "S034",
        "SupplierName": "Stafford-Davis",
        "ContactPerson": "Rhonda Banks",
        "PhoneNumber": "234-503-0888",
        "Email": "carlcampbell@peterson.com",
        "Address": "430 Ryan Villages Apt. 315\nWest Craigberg, MT 27619",
        "ProductCategoriesSupplied": "Kids, Accessories, Women"
    },
    {
        "SupplierID": "S035",
        "SupplierName": "Edwards-Smith",
        "ContactPerson": "Michael Cannon",
        "PhoneNumber": "293-855-9211",
        "Email": "jacobsonjeffrey@gmail.com",
        "Address": "891 Brown Plains\nMichaelmouth, IL 49907",
        "ProductCategoriesSupplied": "Kids, Women"
    },
    {
        "SupplierID": "S036",
        "SupplierName": "Martin, Mora and Andrews",
        "ContactPerson": "William Harris",
        "PhoneNumber": "(184)606-9153x94228",
        "Email": "devin94@padilla-conley.com",
        "Address": "6222 Aguilar Glen Apt. 746\nMoorefurt, CO 87216",
        "ProductCategoriesSupplied": "Men, Accessories"
    },
    {
        "SupplierID": "S037",
        "SupplierName": "Brown-Williams",
        "ContactPerson": "Scott Livingston",
        "PhoneNumber": "613-397-3961",
        "Email": "hannahrodriguez@moore-james.com",
        "Address": "2986 Stein Dam Suite 590\nEast Jessicaview, NM 66559",
        "ProductCategoriesSupplied": "Accessories, Men"
    },
    {
        "SupplierID": "S038",
        "SupplierName": "Smith-Wilkerson",
        "ContactPerson": "Sandra Hall",
        "PhoneNumber": "5702123885",
        "Email": "gmartin@salazar.info",
        "Address": "30416 Davis Plains Apt. 176\nWest Justintown, CO 20965",
        "ProductCategoriesSupplied": "Kids, Women, Accessories"
    },
    {
        "SupplierID": "S039",
        "SupplierName": "Glenn, Foster and Wood",
        "ContactPerson": "Denise Browning",
        "PhoneNumber": "(506)589-6246",
        "Email": "gking@hotmail.com",
        "Address": "4596 Davis Crossing\nStephensburgh, IA 85649",
        "ProductCategoriesSupplied": "Kids, Men, Accessories"
    },
    {
        "SupplierID": "S040",
        "SupplierName": "Woods, Kelly and Frazier",
        "ContactPerson": "Amy Jones",
        "PhoneNumber": "238.021.0274",
        "Email": "thompsonrobert@brewer-morgan.info",
        "Address": "60398 Michele Shores Apt. 399\nEast Joanna, ND 27998",
        "ProductCategoriesSupplied": "Kids, Men"
    },
    {
        "SupplierID": "S041",
        "SupplierName": "Blair PLC",
        "ContactPerson": "Melanie Williams",
        "PhoneNumber": "6742289007",
        "Email": "hardykayla@hotmail.com",
        "Address": "Unit 5879 Box 6951\nDPO AA 13083",
        "ProductCategoriesSupplied": "Women, Accessories"
    },
    {
        "SupplierID": "S042",
        "SupplierName": "Smith Group",
        "ContactPerson": "Tina Allen",
        "PhoneNumber": "(984)071-6091",
        "Email": "sheila13@hotmail.com",
        "Address": "0628 Bond Lock\nEast Jason, GA 96240",
        "ProductCategoriesSupplied": "Accessories, Women, Kids"
    },
    {
        "SupplierID": "S043",
        "SupplierName": "Gonzalez-Bush",
        "ContactPerson": "Diana Gross",
        "PhoneNumber": "840.459.5214",
        "Email": "tommy21@yahoo.com",
        "Address": "00657 Ryan Common\nNorth Allison, AK 66658",
        "ProductCategoriesSupplied": "Women, Men, Accessories"
    },
    {
        "SupplierID": "S044",
        "SupplierName": "Jones Inc",
        "ContactPerson": "Justin Lamb",
        "PhoneNumber": "+1-809-907-0764x59593",
        "Email": "carolfisher@soto.net",
        "Address": "0694 Stephanie Squares Apt. 029\nSouth Sharishire, VT 07549",
        "ProductCategoriesSupplied": "Accessories, Men"
    },
    {
        "SupplierID": "S045",
        "SupplierName": "Holmes, Mendez and Foster",
        "ContactPerson": "Steven Thompson",
        "PhoneNumber": "(694)032-2057",
        "Email": "shermanleslie@hotmail.com",
        "Address": "Unit 5105 Box 8761\nDPO AP 90250",
        "ProductCategoriesSupplied": "Men, Kids"
    },
    {
        "SupplierID": "S046",
        "SupplierName": "Gibson PLC",
        "ContactPerson": "Shannon Harper",
        "PhoneNumber": "351-979-7319",
        "Email": "chelseasmith@hotmail.com",
        "Address": "15329 Jones Coves\nWest Gregorytown, RI 36962",
        "ProductCategoriesSupplied": "Kids, Accessories, Men"
    },
    {
        "SupplierID": "S047",
        "SupplierName": "Salazar, Torres and Jordan",
        "ContactPerson": "Veronica James",
        "PhoneNumber": "(054)781-5929x5701",
        "Email": "warrenluke@richard.biz",
        "Address": "75060 Deanna Viaduct\nNorth Kimberly, NC 30056",
        "ProductCategoriesSupplied": "Kids, Women"
    },
    {
        "SupplierID": "S048",
        "SupplierName": "Maldonado, Hudson and Collins",
        "ContactPerson": "Kim Salinas",
        "PhoneNumber": "171.399.6702",
        "Email": "nelsoncaitlin@hotmail.com",
        "Address": "4359 Sullivan Path Apt. 881\nJensenton, NC 21451",
        "ProductCategoriesSupplied": "Accessories"
    },
    {
        "SupplierID": "S049",
        "SupplierName": "Salinas-Harris",
        "ContactPerson": "Benjamin Barnes",
        "PhoneNumber": "944-172-6467x9074",
        "Email": "pamela05@gmail.com",
        "Address": "9205 Johnston Mews Suite 493\nJameston, SD 42372",
        "ProductCategoriesSupplied": "Accessories, Women"
    },
    {
        "SupplierID": "S050",
        "SupplierName": "Martinez, Moore and Lee",
        "ContactPerson": "Ashley Snyder",
        "PhoneNumber": "067.351.5947x82724",
        "Email": "bmcfarland@atkinson.com",
        "Address": "5275 Lauren Inlet Apt. 683\nLake Stevefurt, NC 79896",
        "ProductCategoriesSupplied": "Men, Women, Kids"
    }
]